setup.py
ResearchDataAU.egg-info/PKG-INFO
ResearchDataAU.egg-info/SOURCES.txt
ResearchDataAU.egg-info/dependency_links.txt
ResearchDataAU.egg-info/requires.txt
ResearchDataAU.egg-info/top_level.txt
researchdata_au/__init__.py
researchdata_au/api.py