Metadata-Version: 1.1
Name: ResearchDataAU
Version: 0.1.2
Summary: A Python 3 API for researchdata.ands.org.au
Home-page: https://github.com/dawoudt/Research-Data-Australia-API
Author: Dawoud Tabboush
Author-email: dtabboush@gmail.com
License: MIT
Keywords: research data Australia academic university
Platform: any
Classifier: Development Status :: 4 - Beta
Classifier: Intended Audience :: Developers
Classifier: License :: OSI Approved :: MIT License
Classifier: Operating System :: OS Independent
Classifier: Programming Language :: Python
Classifier: Programming Language :: Python :: 3
Classifier: Topic :: Software Development :: Libraries :: Python Modules
